ZtjJsonLogging.py
py_ztj_json_logging-1.0.0.dist-info/LICENSE
py_ztj_json_logging-1.0.0.dist-info/METADATA
py_ztj_json_logging-1.0.0.dist-info/WHEEL
py_ztj_json_logging-1.0.0.dist-info/top_level.txt
py_ztj_json_logging-1.0.0.dist-info/RECORD
