Metadata-Version: 2.1
Name: py-ztj-json-logging
Version: 1.0.0
Summary: python json logging logger formatter
Home-page: https://github.com/ztj1993/py-json-logging
Author: ZhangTianJie
Author-email: ztj1993@gmail.com
License: MIT License
Keywords: json logging logger formatter
Platform: UNKNOWN
